[
    {
      "zero_point": 250.0
    },
    {
      "water_height": 0,
      "flow_rate": 0.0
    },
    {
      "water_height": 11,
      "flow_rate": 0.02
    },
    {
      "water_height": 22,
      "flow_rate": 0.1
    },
    {
      "water_height": 33,
      "flow_rate": 0.28
    },
    {
      "water_height": 44,
      "flow_rate": 0.57
    },
    {
      "water_height": 56,
      "flow_rate": 1.04
    },
    {
      "water_height": 67,
      "flow_rate": 1.63
    },
    {
      "water_height": 78,
      "flow_rate": 2.38
    },
    {
      "water_height": 89,
      "flow_rate": 3.31
    },
    {
      "water_height": 100,
      "flow_rate": 4.43
    }
  ]
  